[
 {
  "date": "2015-12-17 11:21", 
  "link": "http://www.hjenglish.com/new/p759585/", 
  "description": "<a href=\"http://www.hjenglish.com/new/p759585/\"><img src=\"http://www.hjenglish.com/2009/images/rss_shuangyu.gif\" style=\"border: 0;\" /></a><br /><p>\n\t<span style=\"line-height: 1.8em;\">As we reflect on 2015, it's clear that this year has been an incredible one for wedding photography. </span><span style=\"line-height: 1.8em;\">回首2015，今年可以说是婚纱摄影的旺年。</span></p>\n<p>\n\t<span style=\"line-height: 1.8em;\">We combed wedding blogs, pored over Pinterest and enlisted the help of talented photographers to deliver you some of the most remarkable wedding photos of the year. Our favorites are below:</span><span style=\"line-height: 1.8em;\">我们浏览一些婚礼博客，尤其关注了Pinterest网站（一个图片网站），列出了一些优秀摄影师鸣谢名单，为您呈现今年最震撼的结婚照片。以下就是我们挑选出来的照片：</span></p>\n<p>\n\t<img src=\"http://i2.w.hjfile.cn/doc/201512/73f0b42e4cff4d0b9077573cd1b30f2e.jpg\" /></p>\n<p>\n\t<img src=\"http://i2.w.hjfile.cn/doc/201512/7c9ccbb7ec7348c7a9f2d5cc0ec6ed5b.jpg\" /></p>\n<p>\n\t<img src=\"http://i2.w.hjfile.cn/doc/201512/3a7cb20d9373443ea800b4e105723878.jpg\" /></p>\n<p>\n\t<img src=\"http://i2.w.hjfile.cn/doc/201512/893886854a784cf39c3b4604e95ef44b.jpg\" /></p>\n<p>\n\t<img src=\"http://i2.w.hjfile.cn/doc/201512/c728996c49994c43b55f6545cd9d8b65.jpg\" /></p>\n<p>\n\t<img src=\"http://i2.w.hjfile.cn/doc/201512/f2aaf24fb600412b9054df3894647844.jpg\" /></p>\n<p>\n\t<img src=\"http://i2.w.hjfile.cn/doc/201512/fda1d57d5029411a9d16c822fef3d1c2.jpg\" /></p>\n<p>\n\t<img src=\"http://i2.w.hjfile.cn/doc/201512/85537f5d9e5f4601843f002badba12d3.jpg\" /></p>\n<p>\n\t<img src=\"http://i2.w.hjfile.cn/doc/201512/2e67a690800a432d9d8582477f1ecd38.jpg\" /></p>\n<p>\n\t<img src=\"http://i2.w.hjfile.cn/doc/201512/bfd6b29e9acb49ee91251cf2de42bd32.jpg\" /></p>\n<p>\n\t<img src=\"http://i2.w.hjfile.cn/doc/201512/56e93add711741598d47af14c8650df4.jpg\" /></p>\n<p>\n\t<img src=\"http://i2.w.hjfile.cn/doc/201512/73166b6696be4b85bb14d77ebf37b0e0.jpg\" /></p>\n<p>\n\t<img src=\"http://i2.w.hjfile.cn/doc/201512/45b0bf064218410c8be77170857ee984.jpg\" /></p>\n<p>\n\t<img src=\"http://i2.w.hjfile.cn/doc/201512/24e849b841764c69839925a3deac42a6.jpg\" /></p>\n<p>\n\t<img src=\"http://i2.w.hjfile.cn/doc/201512/00c677c2b2a9445981a770450cf267a9.jpg\" /></p>\n<p style=\"font-size: 12px; color: #999999;\">\n\t声明：本双语文章的中文翻译系沪江英语原创内容，转载请注明出处。中文翻译仅代表译者个人观点，仅供参考。如有不妥之处，欢迎指正。</p>\n<br /><center><a href=\"http://www.hjenglish.com/new/p759585/#relate_articles\"><img src=\"http://en.hujiang.com/2009/images/rss_chat.jpg\" style=\"border: 0;\" /></a> <a href=\"http://www.hjenglish.com/new/p759585\"><img src=\"http://en.hujiang.com/2009/images/rss_digg.jpg\" style=\"border: 0;\" /></a></center><h3 style=\"margin: 10px;\">本周最热文章</h3><ul style=\"margin: 5px 0;\"><li style=\"margin: 2px 0 2px 20px;\"><a href=\"http://en.hujiang.com/new/p759082/\">2015年12月英语四六级干货福利大放送啦！</a></li><li style=\"margin: 2px 0 2px 20px;\"><a href=\"http://en.hujiang.com/new/p759421/\">BBC：哪个猝不及防的瞬间你爱上了这个世界</a></li><li style=\"margin: 2px 0 2px 20px;\"><a href=\"http://en.hujiang.com/new/p759169/\">优质男的9大特征：你男朋友占几项？</a></li><li style=\"margin: 2px 0 2px 20px;\"><a href=\"http://en.hujiang.com/new/p759389/\">华盛顿邮报力荐2015十佳读物 你看了吗</a></li><li style=\"margin: 2px 0 2px 20px;\"><a href=\"http://en.hujiang.com/new/p759407/\">囧研究：Lie to Me 从眼神手势识破撒谎者！</a></li><li style=\"margin: 2px 0 2px 20px;\"><a href=\"http://en.hujiang.com/new/p758936/\">一样的姿势童年VS成年组图：说好的气质呢？</a></li><li style=\"margin: 2px 0 2px 20px;\"><a href=\"http://en.hujiang.com/new/p759429/\">雪景婚纱照惊艳：冰雪奇缘 来自冬天的祝福</a></li><li style=\"margin: 2px 0 2px 20px;\"><a href=\"http://en.hujiang.com/new/p759540/\">第二届世界互联网大会：8大亮点抢先看</a></li><li style=\"margin: 2px 0 2px 20px;\"><a href=\"http://en.hujiang.com/new/p753807/\">给你两分钟，看懂四六级考卷</a></li><li style=\"margin: 2px 0 2px 20px;\"><a href=\"http://en.hujiang.com/new/p754886/\">超实用攻略：旅行时如何充分利用时间</a></li></ul><div style=\"margin-top: 10px;\">导航:  <a href=\"http://www.hujiang.com/\" style=\"margin: 5px;\" target=\"_black\">沪江网</a>  <a href=\"http://www.hjenglish.com/\" style=\"margin: 5px;\" target=\"_black\">沪江英语</a>  <a href=\"http://jp.hujiang.com/\" style=\"margin: 5px;\" target=\"_black\">沪江日语</a>  <a href=\"http://fr.hujiang.com/\" style=\"margin: 5px;\" target=\"_black\">沪江法语</a>  <a href=\"http://kr.hujiang.com\" style=\"margin: 5px;\" target=\"_black\">沪江韩语</a></div><hr style=\"border: 0.5px solid gray;\" />", 
  "title": "2015年必看结婚照：哪张感动了你"
 }, 
 {
  "date": "2015-12-17 11:20", 
  "link": "http://www.hjenglish.com/new/p759430/", 
  "description": "<a href=\"http://www.hjenglish.com/new/p759430/\"><img src=\"http://www.hjenglish.com/2009/images/rss_shuangyu.gif\" style=\"border: 0;\" /></a><br /><p>\n\t<img src=\"http://i2.w.hjfile.cn/doc/201512/a4cd186071af405bae11e50369448410.jpg\" /></p>\n<p>\n\t<span style=\"line-height: 1.8em;\">Choosing a Christmas gift is always a stressful time but scientists say it should be surprisingly easier than you think, claiming you should choose something you like rather than guessing what they want.</span><span style=\"line-height: 1.8em;\">挑圣诞节礼物通常都会让人感到鸭梨山大。但科学家称挑礼物远比你想象得简单得多，科学家还说你应该挑你喜欢的东西而不是猜收礼物的人喜欢什么。&nbsp;</span></p>\n<p>\n\t<span style=\"line-height: 1.8em;\">The research published in the <em>Journal of Experimental Social Psychology</em> focused on answering the longstanding question: What present should I buy for Christmas and will they actually like my choice of gift?</span><span style=\"line-height: 1.8em;\">一项发表在《实验社会心理学杂志》上的研究回答了这个困扰人们很久的问题：圣诞节我应该要买什么礼物呢？他们会喜欢我挑的礼物吗？</span></p>\n<p>\n\t<span style=\"line-height: 1.8em;\">The new advice may come as surprise for some long suffering shoppers with the study, carried out by psychologists and other researchers, suggesting you don't need to overthink your presents.</span><span style=\"line-height: 1.8em;\">对于那些在这上面深受折磨的人来说，一项新的建议可能会出乎他们的意料。这项由心理学家和其他研究人员所作的意见指出，你没有必要在挑礼物上想太多。</span></p>\n<p>\n\t<img src=\"http://i2.w.hjfile.cn/doc/201512/2757d58ead2e49bc9a300d837c89f8c8.jpg\" /></p>\n<p>\n\tIt found that choosing a present which embodies the 'true self' of the giver is more likely to be in tune with the gift receiver's enjoyment of the present.研究发现，挑选一份体现送礼人&ldquo;真实自我&rdquo;的礼物更有可能会让收礼物的人开心。</p>\n<p>\n\tBuying a present that you think someone will like often leads to disappointment for the receiver.买一份你认为某人会喜欢的礼物通常会让收礼物的人感到失望。</p>\n<p>\n\t'Does anyone receive a present they actually want to keep?' said Professor Adrian Furnham, University College London psychologist.伦敦大学学院心理学家艾德里安&middot;弗恩海姆教授说：&ldquo;每个人都能收到自己想要的礼物吗？&rdquo;</p>\n<p>\n\t'There appears to be no relationship between the cost of a gift and the extent to which it is liked or preferred,' wrote Professor Furnham.弗恩海姆教授写到：&ldquo;事实证明，礼物的贵重与否与收礼物的人对礼物的喜欢或偏好程度没有联系。&rdquo;</p>\n<p>\n\tA study in September found that when 122 university students bought iTune songs as a gift for friends, the recipient tended to like the gift more if it reflected the buyer's personal favourite music.九月份一项研究发现当122名大学生从iTune上买一首歌作为礼物送给朋友时，如果这首歌是购买人个人非常喜欢的歌曲，收礼物的人一般都会更加喜欢这份礼物。</p>\n<p>\n\tSecond guessing what someone wants for Christmas can often lead to a loss in understanding of what those closest to you actually value.反复思量一个人想要什么圣诞礼物通常会让人意识不到那些跟你最亲密之人的真正价值。</p>\n<p>\n\tProfessor Furnham said that the 'subtlety of the exchange' can be most easily seen when the choice of gift turns out to be completely wrong.弗恩海姆教授称，&ldquo;礼物交换的微妙之处&rdquo;通常在挑错礼物的时候最容易看出来。</p>\n<p>\n\tSImilarly researcher found that people who receive a generous main present as well as a smaller, cheaper gift, tend to work out the average value of the set of gifts.研究人员还发现，当人们收到比较贵重的礼物附带一些小的便宜的礼物时，通常会计算所有礼物的平均价值。</p>\n<p>\n\tThe cheaper present in the 'bundle gift' approach tends to devalue the price of the main gift.在&ldquo;一大捆&rdquo;礼物当中，便宜的礼物会拉低贵重礼物的价值。</p>\n<p>\n\tResearchers also gave some handy advice for couples, warning about the dangers of giving presents of great cost too early in the relationship, leading to over-hyped expectations.研究人员还给情侣们提了一些很实用的建议，向他们指出过早送太贵重礼物的危险性，这通常会让对方（对以后将收到的礼物）表现出过于夸张的期望。</p>\n<div>\n\t<p style=\"font-size: 12px; color: #999999;\">\n\t\t声明：本双语文章的中文翻译系沪江英语原创内容，转载请注明出处。中文翻译仅代表译者个人观点，仅供参考。如有不妥之处，欢迎指正。</p>\n</div>\n<br /><center><a href=\"http://www.hjenglish.com/new/p759430/#relate_articles\"><img src=\"http://en.hujiang.com/2009/images/rss_chat.jpg\" style=\"border: 0;\" /></a> <a href=\"http://www.hjenglish.com/new/p759430\"><img src=\"http://en.hujiang.com/2009/images/rss_digg.jpg\" style=\"border: 0;\" /></a></center><h3 style=\"margin: 10px;\">本周最热文章</h3><ul style=\"margin: 5px 0;\"><li style=\"margin: 2px 0 2px 20px;\"><a href=\"http://en.hujiang.com/new/p759082/\">2015年12月英语四六级干货福利大放送啦！</a></li><li style=\"margin: 2px 0 2px 20px;\"><a href=\"http://en.hujiang.com/new/p759421/\">BBC：哪个猝不及防的瞬间你爱上了这个世界</a></li><li style=\"margin: 2px 0 2px 20px;\"><a href=\"http://en.hujiang.com/new/p759169/\">优质男的9大特征：你男朋友占几项？</a></li><li style=\"margin: 2px 0 2px 20px;\"><a href=\"http://en.hujiang.com/new/p759389/\">华盛顿邮报力荐2015十佳读物 你看了吗</a></li><li style=\"margin: 2px 0 2px 20px;\"><a href=\"http://en.hujiang.com/new/p759407/\">囧研究：Lie to Me 从眼神手势识破撒谎者！</a></li><li style=\"margin: 2px 0 2px 20px;\"><a href=\"http://en.hujiang.com/new/p758936/\">一样的姿势童年VS成年组图：说好的气质呢？</a></li><li style=\"margin: 2px 0 2px 20px;\"><a href=\"http://en.hujiang.com/new/p759429/\">雪景婚纱照惊艳：冰雪奇缘 来自冬天的祝福</a></li><li style=\"margin: 2px 0 2px 20px;\"><a href=\"http://en.hujiang.com/new/p759540/\">第二届世界互联网大会：8大亮点抢先看</a></li><li style=\"margin: 2px 0 2px 20px;\"><a href=\"http://en.hujiang.com/new/p753807/\">给你两分钟，看懂四六级考卷</a></li><li style=\"margin: 2px 0 2px 20px;\"><a href=\"http://en.hujiang.com/new/p754886/\">超实用攻略：旅行时如何充分利用时间</a></li></ul><div style=\"margin-top: 10px;\">导航:  <a href=\"http://www.hujiang.com/\" style=\"margin: 5px;\" target=\"_black\">沪江网</a>  <a href=\"http://www.hjenglish.com/\" style=\"margin: 5px;\" target=\"_black\">沪江英语</a>  <a href=\"http://jp.hujiang.com/\" style=\"margin: 5px;\" target=\"_black\">沪江日语</a>  <a href=\"http://fr.hujiang.com/\" style=\"margin: 5px;\" target=\"_black\">沪江法语</a>  <a href=\"http://kr.hujiang.com\" style=\"margin: 5px;\" target=\"_black\">沪江韩语</a></div><hr style=\"border: 0.5px solid gray;\" />", 
  "title": "纠结圣诞节送啥？科学家来支招 保证ta喜欢"
 }
]