[
 {
  "date": "2015-06-09 06:00", 
  "link": "http://www.hjenglish.com/new/p731857/", 
  "description": "<p>\n\t<img src=\"http://i2.w.hjfile.cn/doc/201505/4809522546bf48b5ba3d1d5a33620040.jpg\" style=\"height: 306px; width: 460px;\" /></p>\n<p>\n\t<span style=\"font-size: 14px; line-height: 1.8em;\">本节目为沪江部落一档美语发音模仿节目，每期节目选取30秒左右的慢速VOA新闻内容，主持人亲自朗读示范模仿发音，对发音要点进行讲解，并配以详细的语音语调示意图，手把手教你练就地道美音范儿！想要得到主持人专业的点评和意见吗？</span></p>\n<p>\n\t<a href=\"http://pass.hujiang.com/signup/?source=en_sqyd&amp;url=http://bulo.hujiang.com/app/menu/11885/\" style=\"line-height: 1.8em;\" target=\"_blank\"><img src=\"http://i2.w.yun.hjfile.cn/doc/201304/d5e293c817a6488d819f0c13a95230e1.jpg\" style=\"line-height: 1.8em;\" /></a><span style=\"line-height: 1.8em;\">去沪江部落订阅本节目！</span></p>\n<p>\n\t<strong style=\"line-height: 1.8em;\">今日主持人：</strong><strong><span style=\"font-size: 14px; line-height: 1.8em;\">Mornight</span></strong></p>\n<p>\n\t<strong style=\"font-size: 14px; line-height: 1.8em;\">30秒音频：</strong></p>\n<p>\n\t<a href=\"http://www.hjenglish.com/new/p731857\" title=\"点击获得更好的阅读体验\"><img src=\"http://www.hjenglish.com/2009/images/rss_video.gif\" /></a></p>\n<p>\n\t<strong style=\"line-height: 1.8em;\">主</strong><strong style=\"line-height: 1.8em;\">持人模仿音频：</strong></p>\n<p>\n\t<a href=\"http://www.hjenglish.com/new/p731857\" title=\"点击获得更好的阅读体验\"><img src=\"http://www.hjenglish.com/2009/images/rss_video.gif\" /></a></p>\n<p>\n\t<strong style=\"line-height: 1.8em;\">模仿文本：</strong></p>\n<p>\n\tMr. Obama says that, with the <a class=\"hjdict\" href=\"http://dict.hjenglish.com/w/economy\" target=\"_blank\">economy</a> stronger, he is able to work on what he calls &quot;long-term&quot; <a class=\"hjdict\" href=\"http://dict.hjenglish.com/w/project\" target=\"_blank\">projects</a> in national and foreign affairs.奥巴马先生表示在经济越来越强劲的情况下，他可以在国内外事务上开展他所谓的&ldquo;长期&rdquo;计划了。</p>\n<p>\n\t<strong style=\"line-height: 1.8em;\">重点单词发音讲解：</strong></p>\n<p>\n\teconomy [ɪ'kɑnəmi]<br />\n\tproject [ˈprɔdʒɛkt]</p>\n<p>\n\t<span style=\"font-size: 14px; line-height: 1.8em;\">想要得到主持人专业的点评和意见吗<a href=\"http://bulo.hujiang.com/menu/11885/item/817498/\" target=\"_blank\">？</a></span><a href=\"http://st.hujiang.com/topic/161878192108/\" target=\"_blank\"><span style=\"color: rgb(255,0,0);\">快来节目现场一试身手吧&gt;&gt;</span></a><a href=\"http://st.hujiang.com/topic/161833853699/\" target=\"_blank\">&nbsp;</a></p>\n<br /><center><a href=\"http://www.hjenglish.com/new/p731857/#relate_articles\"><img src=\"http://en.hujiang.com/2009/images/rss_chat.jpg\" style=\"border: 0;\" /></a> <a href=\"http://www.hjenglish.com/new/p731857\"><img src=\"http://en.hujiang.com/2009/images/rss_digg.jpg\" style=\"border: 0;\" /></a></center><h3 style=\"margin: 10px;\">本周最热文章</h3><ul style=\"margin: 5px 0;\"><li style=\"margin: 2px 0 2px 20px;\"><a href=\"http://en.hujiang.com/new/p733802/\">你们城里人真会玩儿：雷倒老外的神翻译</a></li><li style=\"margin: 2px 0 2px 20px;\"><a href=\"http://en.hujiang.com/new/p733670/\">夏天来不及减肥？幻影裙帮你尽显纤细身材</a></li><li style=\"margin: 2px 0 2px 20px;\"><a href=\"http://en.hujiang.com/new/p733967/\">心都萌化了！英国小王子轻吻妹妹</a></li><li style=\"margin: 2px 0 2px 20px;\"><a href=\"http://en.hujiang.com/new/p733984/\">前瞻！即将火爆2030年的9大未来职业</a></li><li style=\"margin: 2px 0 2px 20px;\"><a href=\"http://en.hujiang.com/new/p733963/\">励志！英截肢姑娘变身美艳模特</a></li><li style=\"margin: 2px 0 2px 20px;\"><a href=\"http://en.hujiang.com/new/p733603/\">毕业后时光：十招来个自我升级</a></li><li style=\"margin: 2px 0 2px 20px;\"><a href=\"http://en.hujiang.com/new/p733800/\">四种永远复数的单词你知道吗？</a></li><li style=\"margin: 2px 0 2px 20px;\"><a href=\"http://en.hujiang.com/new/p733923/\">No Zuo No Die：英国男子碰瓷被判\"反社会\"</a></li><li style=\"margin: 2px 0 2px 20px;\"><a href=\"http://en.hujiang.com/new/p733811/\">英雄联盟里的四六级单词 德玛西亚之力篇</a></li><li style=\"margin: 2px 0 2px 20px;\"><a href=\"http://en.hujiang.com/new/p734007/\">Uber CEO：洗白还需要些日子</a></li></ul><div style=\"margin-top: 10px;\">导航:  <a href=\"http://www.hujiang.com/\" style=\"margin: 5px;\" target=\"_black\">沪江网</a>  <a href=\"http://www.hjenglish.com/\" style=\"margin: 5px;\" target=\"_black\">沪江英语</a>  <a href=\"http://jp.hujiang.com/\" style=\"margin: 5px;\" target=\"_black\">沪江日语</a>  <a href=\"http://fr.hujiang.com/\" style=\"margin: 5px;\" target=\"_black\">沪江法语</a>  <a href=\"http://kr.hujiang.com\" style=\"margin: 5px;\" target=\"_black\">沪江韩语</a></div><hr style=\"border: 0.5px solid gray;\" />", 
  "title": "奥巴马迎来最后两年任期(2/2)"
 }, 
 {
  "date": "2015-06-09 06:00", 
  "link": "http://www.hjenglish.com/new/p729550/", 
  "description": "<p>\n\t<img src=\"http://i2.w.yun.hjfile.cn/doc/201305/c73a3ff60ad94e1ba13db818ca31c2c5.jpg\" /></p>\n<p>\n\t<a href=\"http://pass.hujiang.com/signup/?source=en_sqyd&amp;url=http://bulo.hujiang.com/menu/11921/\" target=\"_blank\">《标准美音模仿秀》</a>是一档沪江部落的原创口语互动节目（<a href=\"http://bulo.hujiang.com/menu/11921/item/937423/\" target=\"_blank\">戳我去参加节目&gt;&gt;</a>），主持人截取30秒左右的英语音频，然后对音频进行重点讲解和示范模仿，并对大家递交的口语模仿作品进行一对一的点评，想要练习纯正美音的童鞋赶快行动起来吧！<a href=\"http://pass.hujiang.com/signup/?source=en_sqyd&amp;url=http://bulo.hujiang.com/menu/11921/\" target=\"_blank\"><img src=\"http://i2.w.yun.hjfile.cn/doc/201304/d5e293c817a6488d819f0c13a95230e1.jpg\" style=\"line-height: 1.8em;\" /></a>去沪江部落订阅本节目！</p>\n<p>\n\t今日主持人：<strong><span style=\"line-height: 1.8em;\">refl</span></strong></p>\n<p>\n\t20秒音频：<a href=\"http://www.hjenglish.com/new/p729550\" title=\"点击获得更好的阅读体验\"><img src=\"http://www.hjenglish.com/2009/images/rss_video.gif\" /></a></p>\n<p>\n\t小编模仿音频：<strong>&nbsp;</strong><a href=\"http://www.hjenglish.com/new/p729550\" title=\"点击获得更好的阅读体验\"><img src=\"http://www.hjenglish.com/2009/images/rss_video.gif\" /></a></p>\n<p>\n\t模仿文本： The only way to end this situation is an <a class=\"hjdict\" href=\"http://dict.hjenglish.com/w/immediate\" target=\"_blank\">immediate</a> <a class=\"hjdict\" href=\"http://dict.hjenglish.com/w/cessation\" target=\"_blank\">cessation</a> of hostilities based on a return to the November 2012 cease-fire agreement between Israel and Hamas. Too much innocent blood has been shed, Ambassador Power said in <a class=\"hjdict\" href=\"http://dict.hjenglish.com/w/conclusion\" target=\"_blank\">conclusion</a>, the suffering of <a class=\"hjdict\" href=\"http://dict.hjenglish.com/w/innocent\" target=\"_blank\">innocent</a> civilians must come to an end.唯一能够结束这种局面的方法是立即停止敌对行动，回归2012年以色列和哈马斯签订停火协议的初衷。太多平民无辜流血牺牲，鲍尔大使总结道，无辜贫民的受难必须终止。<span style=\"line-height: 1.8em;\"></span></p>\n<p>\n\t重点单词发音讲解：<a href=\"http://www.hjenglish.com/new/p729550\" title=\"点击获得更好的阅读体验\"><img src=\"http://www.hjenglish.com/2009/images/rss_video.gif\" /></a></p>\n<p>\n\t重点单词发音图解：<br />\n\t<a href=\"http://i1.s.hjfile.cn/entry/201407/c44eb159-3ca9-4b59-9998-c065fc5fcf11.png\" target=\"_blank\"><img alt=\"点击查看大图\" border=\"0\" src=\"http://i1.s.hjfile.cn/entry/201407/c44eb159-3ca9-4b59-9998-c065fc5fcf11.png\" /></a></p>\n<p>\n\t想要得到主持人专业的点评和意见吗？<a href=\"http://bulo.hujiang.com/menu/11921/item/937423/\" target=\"_blank\">快来节目现场一试身手吧&gt;&gt;</a></p>\n<br /><center><a href=\"http://www.hjenglish.com/new/p729550/#relate_articles\"><img src=\"http://en.hujiang.com/2009/images/rss_chat.jpg\" style=\"border: 0;\" /></a> <a href=\"http://www.hjenglish.com/new/p729550\"><img src=\"http://en.hujiang.com/2009/images/rss_digg.jpg\" style=\"border: 0;\" /></a></center><h3 style=\"margin: 10px;\">本周最热文章</h3><ul style=\"margin: 5px 0;\"><li style=\"margin: 2px 0 2px 20px;\"><a href=\"http://en.hujiang.com/new/p733802/\">你们城里人真会玩儿：雷倒老外的神翻译</a></li><li style=\"margin: 2px 0 2px 20px;\"><a href=\"http://en.hujiang.com/new/p733670/\">夏天来不及减肥？幻影裙帮你尽显纤细身材</a></li><li style=\"margin: 2px 0 2px 20px;\"><a href=\"http://en.hujiang.com/new/p733967/\">心都萌化了！英国小王子轻吻妹妹</a></li><li style=\"margin: 2px 0 2px 20px;\"><a href=\"http://en.hujiang.com/new/p733984/\">前瞻！即将火爆2030年的9大未来职业</a></li><li style=\"margin: 2px 0 2px 20px;\"><a href=\"http://en.hujiang.com/new/p733963/\">励志！英截肢姑娘变身美艳模特</a></li><li style=\"margin: 2px 0 2px 20px;\"><a href=\"http://en.hujiang.com/new/p733603/\">毕业后时光：十招来个自我升级</a></li><li style=\"margin: 2px 0 2px 20px;\"><a href=\"http://en.hujiang.com/new/p733800/\">四种永远复数的单词你知道吗？</a></li><li style=\"margin: 2px 0 2px 20px;\"><a href=\"http://en.hujiang.com/new/p733923/\">No Zuo No Die：英国男子碰瓷被判\"反社会\"</a></li><li style=\"margin: 2px 0 2px 20px;\"><a href=\"http://en.hujiang.com/new/p733811/\">英雄联盟里的四六级单词 德玛西亚之力篇</a></li><li style=\"margin: 2px 0 2px 20px;\"><a href=\"http://en.hujiang.com/new/p734007/\">Uber CEO：洗白还需要些日子</a></li></ul><div style=\"margin-top: 10px;\">导航:  <a href=\"http://www.hujiang.com/\" style=\"margin: 5px;\" target=\"_black\">沪江网</a>  <a href=\"http://www.hjenglish.com/\" style=\"margin: 5px;\" target=\"_black\">沪江英语</a>  <a href=\"http://jp.hujiang.com/\" style=\"margin: 5px;\" target=\"_black\">沪江日语</a>  <a href=\"http://fr.hujiang.com/\" style=\"margin: 5px;\" target=\"_black\">沪江法语</a>  <a href=\"http://kr.hujiang.com\" style=\"margin: 5px;\" target=\"_black\">沪江韩语</a></div><hr style=\"border: 0.5px solid gray;\" />", 
  "title": "美国致力于停止哈以冲突 (2/2)"
 }, 
 {
  "date": "2015-06-09 06:00", 
  "link": "http://www.hjenglish.com/new/p731023/", 
  "description": "<p>\n\t<img src=\"http://i2.w.yun.hjfile.cn/doc/201305/c28f6ed441d84c13acf7cc6a9db85cd1.jpg\" /></p>\n<p>\n\t还在羡慕BBC播音员员一口地道标准的英式发音吗？想要练就纯正英音，《BBC英音模仿秀》帮你忙！《BBC英音模仿秀》是一档沪江部落的原创口语互动节目，主持人对音频进行重点讲解和示范模仿，并对大家递交的口语模仿作品进行一对一的点评！<a href=\"http://pass.hujiang.com/signup/?source=en_sqyd&amp;url=http://st.hujiang.com/133721224/?key=【BBC英音模仿秀】\" target=\"_blank\"><img src=\"http://i2.w.yun.hjfile.cn/doc/201305/7e2a59a999f44c92a141bbeff7458379.jpg\" /></a>去沪江部落订阅本节目！</p>\n<p>\n\t<strong>今日主持人：xhlwrb</strong></p>\n<p>\n\t<strong>10秒音频： </strong><a href=\"http://www.hjenglish.com/new/p731023\" title=\"点击获得更好的阅读体验\"><img src=\"http://www.hjenglish.com/2009/images/rss_video.gif\" /></a></p>\n<p>\n\t<strong>主持人模仿音频： </strong><a href=\"http://www.hjenglish.com/new/p731023\" title=\"点击获得更好的阅读体验\"><img src=\"http://www.hjenglish.com/2009/images/rss_video.gif\" /></a></p>\n<p>\n\t<strong>主持人讲解音频： </strong><a href=\"http://www.hjenglish.com/new/p731023\" title=\"点击获得更好的阅读体验\"><img src=\"http://www.hjenglish.com/2009/images/rss_video.gif\" /></a></p>\n<p>\n\t<strong>模仿文本：</strong></p>\n<div class=\"langs_en\">\n\t<div class=\"langs_en\">\n\t\tThat was The 6th of May 2010 you may remember US stocks <a class=\"hjdict\" href=\"http://dict.hjenglish.com/w/plunge\" target=\"_blank\">plunge</a>d 600 points in five minutes. Regulators there think that 36-year-old Navinder Singh Sarao, a British-based high-frequency trader <a class=\"hjdict\" href=\"http://dict.hjenglish.com/w/manipulate\" target=\"_blank\">manipulate</a>d the market on that day.那是2010年5月的第六天，你可能还记得，美国股市在五分钟内暴跌600点。监管机构认为36岁的Navinder Singh Sarao，一个英国的高频交易者操纵了那天的金融市场。</div>\n</div>\n<p>\n\t<strong>语调示意图：</strong></p>\n<p>\n\t<strong><strong style=\"font-size: 14px; line-height: 22px;\"><span><strong><span><span><strong><strong><span><strong><span><strong><span><span>&nbsp;</span><span><strong><a href=\"http://i3.s.7.hjfile.cn/entry/201504/6152148d-b31b-4ce7-bcf6-a7f44e3046c7.png\"><img src=\"http://i3.s.7.hjfile.cn/entry/201504/6152148d-b31b-4ce7-bcf6-a7f44e3046c7.png\" style=\"border-left-width: 0px; height: 214px; border-right-width: 0px; width: 600px; border-bottom-width: 0px; border-top-width: 0px;\" /></a></strong></span></span></strong></span></strong></span></strong></strong></span></span></strong></span></strong></strong><br />\n\t<strong>重点单词发音讲解：</strong><span style=\"display: none;\">&nbsp;</span></p>\n<p>\n\tplunge</p>\n<p>\n\tmanipulate&nbsp;</p>\n<p>\n\t想要得到主持人专业的点评和意见吗？<a href=\"http://st.hujiang.com/topic/163430441786/\" target=\"_blank\">快来节目现场一试身手吧&gt;&gt;&nbsp;</a></p>\n<br /><center><a href=\"http://www.hjenglish.com/new/p731023/#relate_articles\"><img src=\"http://en.hujiang.com/2009/images/rss_chat.jpg\" style=\"border: 0;\" /></a> <a href=\"http://www.hjenglish.com/new/p731023\"><img src=\"http://en.hujiang.com/2009/images/rss_digg.jpg\" style=\"border: 0;\" /></a></center><h3 style=\"margin: 10px;\">本周最热文章</h3><ul style=\"margin: 5px 0;\"><li style=\"margin: 2px 0 2px 20px;\"><a href=\"http://en.hujiang.com/new/p733802/\">你们城里人真会玩儿：雷倒老外的神翻译</a></li><li style=\"margin: 2px 0 2px 20px;\"><a href=\"http://en.hujiang.com/new/p733670/\">夏天来不及减肥？幻影裙帮你尽显纤细身材</a></li><li style=\"margin: 2px 0 2px 20px;\"><a href=\"http://en.hujiang.com/new/p733967/\">心都萌化了！英国小王子轻吻妹妹</a></li><li style=\"margin: 2px 0 2px 20px;\"><a href=\"http://en.hujiang.com/new/p733984/\">前瞻！即将火爆2030年的9大未来职业</a></li><li style=\"margin: 2px 0 2px 20px;\"><a href=\"http://en.hujiang.com/new/p733963/\">励志！英截肢姑娘变身美艳模特</a></li><li style=\"margin: 2px 0 2px 20px;\"><a href=\"http://en.hujiang.com/new/p733603/\">毕业后时光：十招来个自我升级</a></li><li style=\"margin: 2px 0 2px 20px;\"><a href=\"http://en.hujiang.com/new/p733800/\">四种永远复数的单词你知道吗？</a></li><li style=\"margin: 2px 0 2px 20px;\"><a href=\"http://en.hujiang.com/new/p733923/\">No Zuo No Die：英国男子碰瓷被判\"反社会\"</a></li><li style=\"margin: 2px 0 2px 20px;\"><a href=\"http://en.hujiang.com/new/p733811/\">英雄联盟里的四六级单词 德玛西亚之力篇</a></li><li style=\"margin: 2px 0 2px 20px;\"><a href=\"http://en.hujiang.com/new/p734007/\">Uber CEO：洗白还需要些日子</a></li></ul><div style=\"margin-top: 10px;\">导航:  <a href=\"http://www.hujiang.com/\" style=\"margin: 5px;\" target=\"_black\">沪江网</a>  <a href=\"http://www.hjenglish.com/\" style=\"margin: 5px;\" target=\"_black\">沪江英语</a>  <a href=\"http://jp.hujiang.com/\" style=\"margin: 5px;\" target=\"_black\">沪江日语</a>  <a href=\"http://fr.hujiang.com/\" style=\"margin: 5px;\" target=\"_black\">沪江法语</a>  <a href=\"http://kr.hujiang.com\" style=\"margin: 5px;\" target=\"_black\">沪江韩语</a></div><hr style=\"border: 0.5px solid gray;\" />", 
  "title": "BBC模仿秀: 华尔街之狼出庭"
 }, 
 {
  "date": "2015-06-09 06:00", 
  "link": "http://www.hjenglish.com/new/p733607/", 
  "description": "<a href=\"http://www.hjenglish.com/new/p733607/\"><img src=\"http://www.hjenglish.com/2009/images/rss_shuangyu.gif\" style=\"border: 0;\" /></a><br /><p>\n\t<span style=\"color: rgb(128,0,128); line-height: 1.8em;\"><img alt=\"\" src=\"http://i1.s.hjfile.cn/entry/201406/c4eb420a-edc1-4d02-9c43-969dc82f4ef1.jpg\" /></span></p>\n<p>\n\t<span style=\"color: rgb(128,0,128); line-height: 1.8em;\"><strong><a href=\"http://st.hujiang.com/131781224/c2566/\" target=\"_blank\">《英闻天天译》</a></strong></span><span style=\"line-height: 1.8em;\">是一档沪江部落的原创翻译互动节目（</span><span style=\"color: rgb(128,0,128); line-height: 1.8em;\"><a href=\"http://st.hujiang.com/topic/162628641238/\"><strong>戳去参与节目&gt;&gt;&gt;</strong></a></span><span style=\"line-height: 1.8em;\">），主持人提供翻译参考文本，对大家递交的翻译作品进行点评，和大家共同进步！本期节目选</span><span style=\"line-height: 1.8em;\">取的是关于</span>经济影响文学<span style=\"line-height: 1.8em;\">的</span><span style=\"font-family: verdana, helvetica; line-height: 28px;\">一则英文报道，让我们一起在翻译中关注</span><font style=\"line-height: 1.8em;\">。</font></p>\n<p>\n\t<span style=\"color: rgb(0,0,0);\"><span style=\"border-top-width: 0px;\"><span style=\"border-left-width: 0px; font-family: verdana, helvetica; border-right-width: 0px; border-bottom-width: 0px; padding-bottom: 0px; padding-top: 0px; padding-left: 0px; margin: 0px; padding-right: 0px; border-top-width: 0px; border-image: none;\"><span style=\"font-size: 10.5pt; color: red;\"><font color=\"#494949\"><strong>&nbsp;</strong><a href=\"http://i3.s.7.hjfile.cn/entry/201503/a487eea6-638b-460f-a38a-f0ee247623a5.jpg\"><img alt=\"\" src=\"http://i3.s.7.hjfile.cn/entry/201503/a487eea6-638b-460f-a38a-f0ee247623a5.jpg\" style=\"border-left-width: 0px; height: 380px; border-right-width: 0px; width: 600px; border-bottom-width: 0px; border-top-width: 0px;\" /></a></font></span></span></span></span></p>\n<p>\n\t<span style=\"color: rgb(0,0,0);\"><span style=\"border-top-width: 0px;\"><span style=\"border-left-width: 0px; font-family: verdana, helvetica; border-right-width: 0px; border-bottom-width: 0px; padding-bottom: 0px; padding-top: 0px; padding-left: 0px; margin: 0px; padding-right: 0px; border-top-width: 0px; border-image: none;\"><strong>SUMMARY：</strong></span></span></span></p>\n<p>\n\t<span style=\"color: rgb(0,0,0);\"><span style=\"border-top-width: 0px;\"><span style=\"border-left-width: 0px; font-family: verdana, helvetica; border-right-width: 0px; border-bottom-width: 0px; padding-bottom: 0px; padding-top: 0px; padding-left: 0px; margin: 0px; padding-right: 0px; border-top-width: 0px; border-image: none;\"><span style=\"color: rgb(0,0,0);\"><span style=\"color: rgb(0,0,0);\">位于东京西面620英里的西之岛，由于火山喷发，其面积持续增加~~</span></span></span></span></span></p>\n<div>\n\t<strong style=\"line-height: 1.8em;\">CONTENT：</strong></div>\n<div id=\"cke_pastebin\">\n\t<div id=\"cke_pastebin\">\n\t\t<div id=\"cke_pastebin\">\n\t\t\t<div id=\"cke_pastebin\">\n\t\t\t\t<div id=\"cke_pastebin\">\n\t\t\t\t\t<div id=\"cke_pastebin\">\n\t\t\t\t\t\t<div id=\"cke_pastebin\">\n\t\t\t\t\t\t\t<div id=\"cke_pastebin\">\n\t\t\t\t\t\t\t\t<div id=\"cke_pastebin\">\n\t\t\t\t\t\t\t\t\t<div id=\"cke_pastebin\">\n\t\t\t\t\t\t\t\t\t\t<div id=\"cke_pastebin\">\n\t\t\t\t\t\t\t\t\t\t\t<a class=\"hjdict\" href=\"http://dict.hjenglish.com/w/Magma\" target=\"_blank\">Magma</a> and <a class=\"hjdict\" href=\"http://dict.hjenglish.com/w/lava\" target=\"_blank\">lava</a> from a volcanic eruption in the remote Pacific have formed a new island measuring one square mile in size.<br />\n\t\t\t\t\t\t\t\t\t\t\tPhotographs taken of the island of Nishinoshima, since an eruption off its coast in November 20, 2013, reveal the <a class=\"hjdict\" href=\"http://dict.hjenglish.com/w/landmass\" target=\"_blank\">landmass</a> is continuing to increase in size in an extremely rare volcanic phenomenon.<br />\n\t\t\t\t\t\t\t\t\t\t\tThe eruption off the coast of Nishinoshima island - which is located within the Ring of Fire - initially created an <a class=\"hjdict\" href=\"http://dict.hjenglish.com/w/islet\" target=\"_blank\">islet</a> but the volcanic <a class=\"hjdict\" href=\"http://dict.hjenglish.com/w/discharge\" target=\"_blank\">discharge</a> has now merged with it to form a single landmass.&nbsp;</div>\n\t\t\t\t\t\t\t\t\t</div>\n\t\t\t\t\t\t\t\t</div>\n\t\t\t\t\t\t\t</div>\n\t\t\t\t\t\t</div>\n\t\t\t\t\t</div>\n\t\t\t\t</div>\n\t\t\t</div>\n\t\t</div>\n\t</div>\n</div>\n<p>\n\t<span style=\"color: rgb(0,100,0);\"><strong>【沪江英语小编】</strong></span>大家在查看主持人提供的翻译版本前，可以先自己进行尝试翻译练习，只有在不断的翻译中翻译能力才能有所提升哦！<br />\n\t轻松注册沪江，马上参与<strong><a href=\"http://st.hujiang.com/131781224/c2566/\">【英闻天天译】</a></strong>节目练翻译&rarr;<a href=\"http://pass.hujiang.com/signup/?source=en_sqyd&amp;url=http://st.hujiang.com/131781224/c2566/\" target=\"_blank\"><img src=\"http://i2.w.yun.hjfile.cn/doc/201304/810ca373cf4442a188b39dd8ff64425f.jpg\" /></a></p>\n<p>\n\t<strong>本期节目参考译文：</strong><span style=\"color: rgb(128,128,128);\">（参考译文由该节目主持人提供，仅供参考，欢迎大家讨论）</span></p>\n<p>\n\t<span style=\"color: rgb(0,0,0);\"><strong>参考译文1：</strong></span></p>\n<div class=\"replyview red\">\n\t<div id=\"cke_pastebin\">\n\t\t<div id=\"cke_pastebin\">\n\t\t\t<div id=\"cke_pastebin\">\n\t\t\t\t<div id=\"cke_pastebin\">\n\t\t\t\t\t<div id=\"cke_pastebin\">\n\t\t\t\t\t\t<div id=\"cke_pastebin\">\n\t\t\t\t\t\t\t<div id=\"cke_pastebin\">\n\t\t\t\t\t\t\t\t<div id=\"cke_pastebin\">\n\t\t\t\t\t\t\t\t\t<div id=\"cke_pastebin\">\n\t\t\t\t\t\t\t\t\t\t<div id=\"cke_pastebin\">\n\t\t\t\t\t\t\t\t\t\t\t<span style=\"color: rgb(0,0,0);\">在遥远的太平洋，火山喷发出的岩浆和熔岩，形成了一个大小为一平方英里的新岛屿。<br />\n\t\t\t\t\t\t\t\t\t\t\t自从2013年11月20日西岛沿海地区的火山爆发，西之岛（町）的照片就显示其陆地面积由于极其罕见的火山现象而持续增加。<br />\n\t\t\t\t\t\t\t\t\t\t\t西之岛（町）沿海地区的火山爆发&mdash;&mdash;位于太平洋火山带内&mdash;&mdash;最初只是形成了一个小岛，但是现在已经和火山喷发物融合形成了一块独立的陆地。</span></div>\n\t\t\t\t\t\t\t\t\t\t<div>\n\t\t\t\t\t\t\t\t\t\t\t<p>\n\t\t\t\t\t\t\t\t\t\t\t\t<span style=\"color: rgb(0,0,0);\"><span style=\"color: rgb(0,0,0);\"><strong>参考译文2：</strong></span></span></p>\n\t\t\t\t\t\t\t\t\t\t\t<div class=\"replyview red\">\n\t\t\t\t\t\t\t\t\t\t\t\t<div id=\"cke_pastebin\">\n\t\t\t\t\t\t\t\t\t\t\t\t\t<div id=\"cke_pastebin\">\n\t\t\t\t\t\t\t\t\t\t\t\t\t\t<div id=\"cke_pastebin\">\n\t\t\t\t\t\t\t\t\t\t\t\t\t\t\t<div id=\"cke_pastebin\">\n\t\t\t\t\t\t\t\t\t\t\t\t\t\t\t\t<div id=\"cke_pastebin\">\n\t\t\t\t\t\t\t\t\t\t\t\t\t\t\t\t\t<div id=\"cke_pastebin\">\n\t\t\t\t\t\t\t\t\t\t\t\t\t\t\t\t\t\t<div id=\"cke_pastebin\">\n\t\t\t\t\t\t\t\t\t\t\t\t\t\t\t\t\t\t\t<div id=\"cke_pastebin\">\n\t\t\t\t\t\t\t\t\t\t\t\t\t\t\t\t\t\t\t\t<div id=\"cke_pastebin\">\n\t\t\t\t\t\t\t\t\t\t\t\t\t\t\t\t\t\t\t\t\t<div id=\"cke_pastebin\">\n\t\t\t\t\t\t\t\t\t\t\t\t\t\t\t\t\t\t\t\t\t\t<span style=\"color: rgb(0,0,0);\"><span style=\"color: rgb(0,0,0);\">在太平洋一隅，一次火山爆发留下的岩浆和熔岩形成了一座新的岛屿，大小约一平方英里。</span></span><span style=\"color: rgb(0,0,0);\"><span style=\"color: rgb(0,0,0);\"><span style=\"color: rgb(0,0,0);\"><span style=\"color: rgb(0,0,0);\"> </span></span></span></span></div>\n\t\t\t\t\t\t\t\t\t\t\t\t\t\t\t\t\t\t\t\t\t<div>\n\t\t\t\t\t\t\t\t\t\t\t\t\t\t\t\t\t\t\t\t\t\t<span style=\"color: rgb(0,0,0);\"><span style=\"color: rgb(0,0,0);\">根据拍摄的西之岛的照片显示，从2013年11月20日该岛附近的火山爆发以来，新形成的小岛由于极其罕见的火山运动仍在持续扩张。</span></span></div>\n\t\t\t\t\t\t\t\t\t\t\t\t\t\t\t\t\t\t\t\t\t<div>\n\t\t\t\t\t\t\t\t\t\t\t\t\t\t\t\t\t\t\t\t\t\t<span style=\"color: rgb(0,0,0);\"><span style=\"color: rgb(0,0,0);\">西之岛位于环太平洋火山带，该岛海岸附近的那次火山爆发最初形成的只是一个弹丸大的小岛，但现在火山熔岩已与最初的小岛融为一体，自成一片大陆。 </span></span></div>\n\t\t\t\t\t\t\t\t\t\t\t\t\t\t\t\t\t\t\t\t</div>\n\t\t\t\t\t\t\t\t\t\t\t\t\t\t\t\t\t\t\t</div>\n\t\t\t\t\t\t\t\t\t\t\t\t\t\t\t\t\t\t</div>\n\t\t\t\t\t\t\t\t\t\t\t\t\t\t\t\t\t</div>\n\t\t\t\t\t\t\t\t\t\t\t\t\t\t\t\t</div>\n\t\t\t\t\t\t\t\t\t\t\t\t\t\t\t</div>\n\t\t\t\t\t\t\t\t\t\t\t\t\t\t</div>\n\t\t\t\t\t\t\t\t\t\t\t\t\t</div>\n\t\t\t\t\t\t\t\t\t\t\t\t</div>\n\t\t\t\t\t\t\t\t\t\t\t</div>\n\t\t\t\t\t\t\t\t\t\t</div>\n\t\t\t\t\t\t\t\t\t</div>\n\t\t\t\t\t\t\t\t</div>\n\t\t\t\t\t\t\t</div>\n\t\t\t\t\t\t</div>\n\t\t\t\t\t</div>\n\t\t\t\t</div>\n\t\t\t</div>\n\t\t</div>\n\t</div>\n</div>\n<p>\n\t想要得到主持人专业的点评和意见吗？<a href=\"http://st.hujiang.com/topic/162628641238/\" target=\"_blank\"><span style=\"color: rgb(255,0,0);\">快来节目现场一试身手吧&gt;&gt;</span></a></p>\n<br /><center><a href=\"http://www.hjenglish.com/new/p733607/#relate_articles\"><img src=\"http://en.hujiang.com/2009/images/rss_chat.jpg\" style=\"border: 0;\" /></a> <a href=\"http://www.hjenglish.com/new/p733607\"><img src=\"http://en.hujiang.com/2009/images/rss_digg.jpg\" style=\"border: 0;\" /></a></center><h3 style=\"margin: 10px;\">本周最热文章</h3><ul style=\"margin: 5px 0;\"><li style=\"margin: 2px 0 2px 20px;\"><a href=\"http://en.hujiang.com/new/p733802/\">你们城里人真会玩儿：雷倒老外的神翻译</a></li><li style=\"margin: 2px 0 2px 20px;\"><a href=\"http://en.hujiang.com/new/p733670/\">夏天来不及减肥？幻影裙帮你尽显纤细身材</a></li><li style=\"margin: 2px 0 2px 20px;\"><a href=\"http://en.hujiang.com/new/p733967/\">心都萌化了！英国小王子轻吻妹妹</a></li><li style=\"margin: 2px 0 2px 20px;\"><a href=\"http://en.hujiang.com/new/p733984/\">前瞻！即将火爆2030年的9大未来职业</a></li><li style=\"margin: 2px 0 2px 20px;\"><a href=\"http://en.hujiang.com/new/p733963/\">励志！英截肢姑娘变身美艳模特</a></li><li style=\"margin: 2px 0 2px 20px;\"><a href=\"http://en.hujiang.com/new/p733603/\">毕业后时光：十招来个自我升级</a></li><li style=\"margin: 2px 0 2px 20px;\"><a href=\"http://en.hujiang.com/new/p733800/\">四种永远复数的单词你知道吗？</a></li><li style=\"margin: 2px 0 2px 20px;\"><a href=\"http://en.hujiang.com/new/p733923/\">No Zuo No Die：英国男子碰瓷被判\"反社会\"</a></li><li style=\"margin: 2px 0 2px 20px;\"><a href=\"http://en.hujiang.com/new/p733811/\">英雄联盟里的四六级单词 德玛西亚之力篇</a></li><li style=\"margin: 2px 0 2px 20px;\"><a href=\"http://en.hujiang.com/new/p734007/\">Uber CEO：洗白还需要些日子</a></li></ul><div style=\"margin-top: 10px;\">导航:  <a href=\"http://www.hujiang.com/\" style=\"margin: 5px;\" target=\"_black\">沪江网</a>  <a href=\"http://www.hjenglish.com/\" style=\"margin: 5px;\" target=\"_black\">沪江英语</a>  <a href=\"http://jp.hujiang.com/\" style=\"margin: 5px;\" target=\"_black\">沪江日语</a>  <a href=\"http://fr.hujiang.com/\" style=\"margin: 5px;\" target=\"_black\">沪江法语</a>  <a href=\"http://kr.hujiang.com\" style=\"margin: 5px;\" target=\"_black\">沪江韩语</a></div><hr style=\"border: 0.5px solid gray;\" />", 
  "title": "英闻天天译: 日本新陆地"
 }, 
 {
  "date": "2015-06-09 06:00", 
  "link": "http://www.hjenglish.com/new/p731607/", 
  "description": "<p>\n\t<img src=\"http://i2.w.yun.hjfile.cn/doc/201305/ca59b3e726274f518deae8f099b9af1a.jpg\" style=\"border-left-width: 0px; border-right-width: 0px; border-bottom-width: 0px; margin-left: 5px; border-top-width: 0px; margin-right: 5px;\" /></p>\n<p>\n\t《英文天天写》是沪江部落一档写作类节目，其目的在于提升大家的英语写作能力。每期节目主持人都会给出一个话题，积极参加的童鞋还会得到主持人的专业点评哦！想提高英语写作的童鞋千万不要错过哦！<a href=\"http://pass.hujiang.com/signup/?source=en_sqyd&amp;url=http://st.hujiang.com/131781224/c2561/order2/\" style=\"text-decoration: none; color: rgb(0,90,148);\" target=\"_blank\"><img src=\"http://i2.w.yun.hjfile.cn/doc/201304/d5e293c817a6488d819f0c13a95230e1.jpg\" style=\"border-left-width: 0px; border-right-width: 0px; border-bottom-width: 0px; margin-left: 5px; line-height: 1.8em; border-top-width: 0px; margin-right: 5px;\" /></a>去沪江部落订阅本节目！</p>\n<p>\n\t<strong>话题：</strong></p>\n<p>\n\tWriting: imagine a scenario or express your opinion<br />\n\t<a class=\"hjdict\" href=\"http://dict.hjenglish.com/w/Retaliate\" target=\"_blank\">Retaliate</a><br />\n\tRetaliate means to fight back. What is the occasion? Why did one side decide to retaliate? What <a class=\"hjdict\" href=\"http://dict.hjenglish.com/w/tactic\" target=\"_blank\">tactic</a> did that side choose?<br />\n\tThis week's topic: They retaliated... (90-110 words)</p>\n<p>\n\tSuggestions:<br />\n\t1) the student who was bullied retaliated against the bully<br />\n\t2) the country under attack retaliated, i.e. military force, <a class=\"hjdict\" href=\"http://dict.hjenglish.com/w/embargo\" target=\"_blank\">embargo</a>, boycott, economic sanction<br />\n\t3) retaliated against the <a class=\"hjdict\" href=\"http://dict.hjenglish.com/w/brute\" target=\"_blank\">brute</a> force of the authority<br />\n\t4) retaliate to maintain independence<br />\n\t5) Instead of writing a scenario, feel free to comment on the story below.</p>\n<p>\n\t<strong>范例1：</strong></p>\n<p>\n\tHis target headed away from the main gathering, towards a much quieter area in the back. Al followed closely without being to obvious. After turning a couple corners, Al saw that his target was heading towards an exit out of the building. Al intended to follow suit, but somebody suddenly pulled him by his shoulder and grabbed his elbow. For a brief moment, Al thought of retaliating and was about to throw a punch when he heard <a class=\"hjdict\" href=\"http://dict.hjenglish.com/w/commotion\" target=\"_blank\">commotion</a>. It seemed that a small group of people were heading his way.</p>\n<p>\n\t想要得到专业主持人的点评和意见吗？<a href=\"http://st.hujiang.com/topic/163147282796/\" target=\"_blank\">快来节目现场一试身手吧&gt;&gt;</a></p>\n<br /><center><a href=\"http://www.hjenglish.com/new/p731607/#relate_articles\"><img src=\"http://en.hujiang.com/2009/images/rss_chat.jpg\" style=\"border: 0;\" /></a> <a href=\"http://www.hjenglish.com/new/p731607\"><img src=\"http://en.hujiang.com/2009/images/rss_digg.jpg\" style=\"border: 0;\" /></a></center><h3 style=\"margin: 10px;\">本周最热文章</h3><ul style=\"margin: 5px 0;\"><li style=\"margin: 2px 0 2px 20px;\"><a href=\"http://en.hujiang.com/new/p733802/\">你们城里人真会玩儿：雷倒老外的神翻译</a></li><li style=\"margin: 2px 0 2px 20px;\"><a href=\"http://en.hujiang.com/new/p733670/\">夏天来不及减肥？幻影裙帮你尽显纤细身材</a></li><li style=\"margin: 2px 0 2px 20px;\"><a href=\"http://en.hujiang.com/new/p733967/\">心都萌化了！英国小王子轻吻妹妹</a></li><li style=\"margin: 2px 0 2px 20px;\"><a href=\"http://en.hujiang.com/new/p733984/\">前瞻！即将火爆2030年的9大未来职业</a></li><li style=\"margin: 2px 0 2px 20px;\"><a href=\"http://en.hujiang.com/new/p733963/\">励志！英截肢姑娘变身美艳模特</a></li><li style=\"margin: 2px 0 2px 20px;\"><a href=\"http://en.hujiang.com/new/p733603/\">毕业后时光：十招来个自我升级</a></li><li style=\"margin: 2px 0 2px 20px;\"><a href=\"http://en.hujiang.com/new/p733800/\">四种永远复数的单词你知道吗？</a></li><li style=\"margin: 2px 0 2px 20px;\"><a href=\"http://en.hujiang.com/new/p733923/\">No Zuo No Die：英国男子碰瓷被判\"反社会\"</a></li><li style=\"margin: 2px 0 2px 20px;\"><a href=\"http://en.hujiang.com/new/p733811/\">英雄联盟里的四六级单词 德玛西亚之力篇</a></li><li style=\"margin: 2px 0 2px 20px;\"><a href=\"http://en.hujiang.com/new/p734007/\">Uber CEO：洗白还需要些日子</a></li></ul><div style=\"margin-top: 10px;\">导航:  <a href=\"http://www.hujiang.com/\" style=\"margin: 5px;\" target=\"_black\">沪江网</a>  <a href=\"http://www.hjenglish.com/\" style=\"margin: 5px;\" target=\"_black\">沪江英语</a>  <a href=\"http://jp.hujiang.com/\" style=\"margin: 5px;\" target=\"_black\">沪江日语</a>  <a href=\"http://fr.hujiang.com/\" style=\"margin: 5px;\" target=\"_black\">沪江法语</a>  <a href=\"http://kr.hujiang.com\" style=\"margin: 5px;\" target=\"_black\">沪江韩语</a></div><hr style=\"border: 0.5px solid gray;\" />", 
  "title": "英文天天写：Retaliate"
 }, 
 {
  "date": "2015-06-09 06:00", 
  "link": "http://www.hjenglish.com/new/p731824/", 
  "description": "<p>\n\t<img src=\"http://i2.w.yun.hjfile.cn/doc/201410/f60ca38bfb2b48e299d6d71fa1de3cb1.jpg\" style=\"height: 287px; width: 460px;\" /></p>\n<p>\n\t《英乐天天唱》是一档模仿唱歌类节目，目的在于提升大家的英语口语能力。主持人会在每期节目中选取好听的歌曲片段，并给出发音提示和模仿示例。喜欢听音乐的童鞋可要积极参与哦！</p>\n<p>\n\t<img alt=\"\" src=\"http://i1.s.hjfile.cn/entry/201308/39cb7586-e2c4-4c51-a01b-83362c67cc7e.jpg\" /></p>\n<p>\n\tSara Bareilles是（出生在尤里卡加利福尼亚西北部一城市洪堡）的一名创作歌手和钢琴家。她经常被拿来与Fiona Apple, Norah Jones, Joni Mitchell这些与她同类型的知名歌手比较，即便她并没有受过任何正式的声乐和钢琴训练。 在BILLBOARD被HIP-HOP统治的情况下Sara Bareilles凭借LOVE SONG连续几周徘徊在榜单前十，给美国乐坛注入一股清新之风，没有太过花俏繁复、哗众取宠的编曲，突显钢琴的透明与纯净，添份夜晚清凉聆听享受，赶走白日喧闹繁杂恼人之事。值得一听的新生代女歌手。</p>\n<p>\n\t<a href=\"http://www.hjenglish.com/new/p731824\" title=\"点击获得更好的阅读体验\"><img src=\"http://www.hjenglish.com/2009/images/rss_video.gif\" /></a></p>\n<p>\n\tHead under water</p>\n<p>\n\tAnd you tell me To breathe easy for a while</p>\n<p>\n\tThe breathing gets harder Even I know that</p>\n<p>\n\tMade room for me It's too soon to see</p>\n<p>\n\tIf I'm happy in your hands</p>\n<p>\n\tI'm unusually hard to hold on to</p>\n<p>\n\tBlank stares at blank pages</p>\n<p>\n\tNo easy way to say this</p>\n<p>\n\tYou mean well but you make this hard on me</p>\n<p>\n\tI'm not gonna write you a love song</p>\n<p>\n\tCause you ask for it</p>\n<p>\n\tCause you need one</p>\n<p>\n\tYou see, I'm not gonna write you a long song</p>\n<p>\n\tCause you tell me it's make or breakin' this</p>\n<p>\n\tIf you're on your way</p>\n<p>\n\tI'm not gonna write you to stay</p>\n<p>\n\tIf all you have is leavin'I'm gonna need a better reason</p>\n<p>\n\tTo write you a love song</p>\n<p>\n\tToday</p>\n<p>\n\tyeah，Today..</p>\n<p>\n\t模唱：<a href=\"http://www.hjenglish.com/new/p731824\" title=\"点击获得更好的阅读体验\"><img src=\"http://www.hjenglish.com/2009/images/rss_video.gif\" /></a></p>\n<p>\n\t伴奏：<a href=\"http://www.hjenglish.com/new/p731824\" title=\"点击获得更好的阅读体验\"><img src=\"http://www.hjenglish.com/2009/images/rss_video.gif\" /></a></p>\n<p>\n\t<a href=\"http://pass.hujiang.com/signup/?source=en_sqyd&amp;url=http://bulo.hujiang.com/menu/15093/\" target=\"_blank\"><img src=\"http://i2.w.yun.hjfile.cn/doc/201304/d5e293c817a6488d819f0c13a95230e1.jpg\" style=\"line-height: 1.8em;\" /></a>去沪江部落订阅本节目！</p>\n<p>\n\t想要得到主持人专业的点评和意见吗？<a href=\"http://bulo.hujiang.com/menu/15093/item/927691/\" target=\"_blank\">快来节目现场一试身手吧&gt;&gt;</a></p>\n<br /><center><a href=\"http://www.hjenglish.com/new/p731824/#relate_articles\"><img src=\"http://en.hujiang.com/2009/images/rss_chat.jpg\" style=\"border: 0;\" /></a> <a href=\"http://www.hjenglish.com/new/p731824\"><img src=\"http://en.hujiang.com/2009/images/rss_digg.jpg\" style=\"border: 0;\" /></a></center><h3 style=\"margin: 10px;\">本周最热文章</h3><ul style=\"margin: 5px 0;\"><li style=\"margin: 2px 0 2px 20px;\"><a href=\"http://en.hujiang.com/new/p733802/\">你们城里人真会玩儿：雷倒老外的神翻译</a></li><li style=\"margin: 2px 0 2px 20px;\"><a href=\"http://en.hujiang.com/new/p733670/\">夏天来不及减肥？幻影裙帮你尽显纤细身材</a></li><li style=\"margin: 2px 0 2px 20px;\"><a href=\"http://en.hujiang.com/new/p733967/\">心都萌化了！英国小王子轻吻妹妹</a></li><li style=\"margin: 2px 0 2px 20px;\"><a href=\"http://en.hujiang.com/new/p733984/\">前瞻！即将火爆2030年的9大未来职业</a></li><li style=\"margin: 2px 0 2px 20px;\"><a href=\"http://en.hujiang.com/new/p733963/\">励志！英截肢姑娘变身美艳模特</a></li><li style=\"margin: 2px 0 2px 20px;\"><a href=\"http://en.hujiang.com/new/p733603/\">毕业后时光：十招来个自我升级</a></li><li style=\"margin: 2px 0 2px 20px;\"><a href=\"http://en.hujiang.com/new/p733800/\">四种永远复数的单词你知道吗？</a></li><li style=\"margin: 2px 0 2px 20px;\"><a href=\"http://en.hujiang.com/new/p733923/\">No Zuo No Die：英国男子碰瓷被判\"反社会\"</a></li><li style=\"margin: 2px 0 2px 20px;\"><a href=\"http://en.hujiang.com/new/p733811/\">英雄联盟里的四六级单词 德玛西亚之力篇</a></li><li style=\"margin: 2px 0 2px 20px;\"><a href=\"http://en.hujiang.com/new/p734007/\">Uber CEO：洗白还需要些日子</a></li></ul><div style=\"margin-top: 10px;\">导航:  <a href=\"http://www.hujiang.com/\" style=\"margin: 5px;\" target=\"_black\">沪江网</a>  <a href=\"http://www.hjenglish.com/\" style=\"margin: 5px;\" target=\"_black\">沪江英语</a>  <a href=\"http://jp.hujiang.com/\" style=\"margin: 5px;\" target=\"_black\">沪江日语</a>  <a href=\"http://fr.hujiang.com/\" style=\"margin: 5px;\" target=\"_black\">沪江法语</a>  <a href=\"http://kr.hujiang.com\" style=\"margin: 5px;\" target=\"_black\">沪江韩语</a></div><hr style=\"border: 0.5px solid gray;\" />", 
  "title": "英文歌曲天天唱：Love Song"
 }, 
 {
  "date": "2015-06-09 06:00", 
  "link": "http://www.hjenglish.com/new/p731818/", 
  "description": "<p>\n\t<img alt=\"\" src=\"http://origin.arstechnica.com/news.media/solar-storm.jpg\" style=\"height: 310px; width: 400px;\" /></p>\n<p>\n\t<a href=\"http://www.hjenglish.com/new/p731818\" title=\"点击获得更好的阅读体验\"><img src=\"http://www.hjenglish.com/2009/images/rss_video.gif\" /></a></p>\n<p>\n\tOn March 13th, 1989, 6 million people in Canada awoke to no <a class=\"hjdict\" href=\"http://dict.hjenglish.com/w/electricity\" target=\"_blank\">electricity</a>.</p>\n<p>\n\t&quot;There has been a big power failure in Quebec. Most of the province is in darkness, including much of Montreal and Quebec City.&quot;</p>\n<p>\n\tNobody knew why the lights went out, and it was nine hours before most power supplies were restored. Some areas were left dark for days. This was the second time in less than a year that the <a class=\"hjdict\" href=\"http://dict.hjenglish.com/w/grid\" target=\"_blank\">grid</a> had come down, and people were outraged.</p>\n<p>\n\t&quot;Well I think it's becoming a little bit <a class=\"hjdict\" href=\"http://dict.hjenglish.com/w/ridiculous\" target=\"_blank\">ridiculous</a> right now.&quot;</p>\n<p>\n\t&quot;It's a <a class=\"hjdict\" href=\"http://dict.hjenglish.com/w/nonsense\" target=\"_blank\">nonsense</a> what they're doing, you know? They make us pay a lot of money, and they can't give united population a good service.&quot;</p>\n<p>\n\tBut this time it wasn't icy weather here on Earth that caused <a class=\"hjdict\" href=\"http://dict.hjenglish.com/w/equipment\" target=\"_blank\">equipment</a> failures. The culprit was 150 million kilometres away - the Sun, as Judith Hann reported on Tomorrow's World.</p>\n<p>\n\t&quot;It's now become clear that the <a class=\"hjdict\" href=\"http://dict.hjenglish.com/w/aurora\" target=\"_blank\">aurora</a> borealis displays in England we reported last week was a result of what was probably this century's most intense magnetic storm, and it disrupted activity across the globe. North Sea oil drilling stopped because of the danger of mistakenly drilling into an existing oil field. And in space, the sharp increase in <a class=\"hjdict\" href=\"http://dict.hjenglish.com/w/radiation\" target=\"_blank\">radiation</a> may have caused the computer <a class=\"hjdict\" href=\"http://dict.hjenglish.com/w/malfunction\" target=\"_blank\">malfunction</a> that forced the shuttle Discovery to return to Earth earlier than planned.&quot;</p>\n<p>\n\t<span>声明：音视频均来自互联网链接，仅供学习使用。本网站自身不存储、控制、修改被链接的内容。&ldquo;沪江</span><a class=\"creatLinks\" href=\"http://st.hujiang.com/tag/%E8%8B%B1%E8%AF%AD/\" target=\"_blank\" title=\"更多英语内容\">英语</a><span>&rdquo;高度重视知识产权保护。当如发现本网站发布的信息包含有侵犯其著作权的链接内容时，请联系我们，我们将依法采取措施移除相关内容或屏蔽相关链接。</span></p>\n<br /><center><a href=\"http://www.hjenglish.com/new/p731818/#relate_articles\"><img src=\"http://en.hujiang.com/2009/images/rss_chat.jpg\" style=\"border: 0;\" /></a> <a href=\"http://www.hjenglish.com/new/p731818\"><img src=\"http://en.hujiang.com/2009/images/rss_digg.jpg\" style=\"border: 0;\" /></a></center><h3 style=\"margin: 10px;\">本周最热文章</h3><ul style=\"margin: 5px 0;\"><li style=\"margin: 2px 0 2px 20px;\"><a href=\"http://en.hujiang.com/new/p733802/\">你们城里人真会玩儿：雷倒老外的神翻译</a></li><li style=\"margin: 2px 0 2px 20px;\"><a href=\"http://en.hujiang.com/new/p733670/\">夏天来不及减肥？幻影裙帮你尽显纤细身材</a></li><li style=\"margin: 2px 0 2px 20px;\"><a href=\"http://en.hujiang.com/new/p733967/\">心都萌化了！英国小王子轻吻妹妹</a></li><li style=\"margin: 2px 0 2px 20px;\"><a href=\"http://en.hujiang.com/new/p733984/\">前瞻！即将火爆2030年的9大未来职业</a></li><li style=\"margin: 2px 0 2px 20px;\"><a href=\"http://en.hujiang.com/new/p733963/\">励志！英截肢姑娘变身美艳模特</a></li><li style=\"margin: 2px 0 2px 20px;\"><a href=\"http://en.hujiang.com/new/p733603/\">毕业后时光：十招来个自我升级</a></li><li style=\"margin: 2px 0 2px 20px;\"><a href=\"http://en.hujiang.com/new/p733800/\">四种永远复数的单词你知道吗？</a></li><li style=\"margin: 2px 0 2px 20px;\"><a href=\"http://en.hujiang.com/new/p733923/\">No Zuo No Die：英国男子碰瓷被判\"反社会\"</a></li><li style=\"margin: 2px 0 2px 20px;\"><a href=\"http://en.hujiang.com/new/p733811/\">英雄联盟里的四六级单词 德玛西亚之力篇</a></li><li style=\"margin: 2px 0 2px 20px;\"><a href=\"http://en.hujiang.com/new/p734007/\">Uber CEO：洗白还需要些日子</a></li></ul><div style=\"margin-top: 10px;\">导航:  <a href=\"http://www.hujiang.com/\" style=\"margin: 5px;\" target=\"_black\">沪江网</a>  <a href=\"http://www.hjenglish.com/\" style=\"margin: 5px;\" target=\"_black\">沪江英语</a>  <a href=\"http://jp.hujiang.com/\" style=\"margin: 5px;\" target=\"_black\">沪江日语</a>  <a href=\"http://fr.hujiang.com/\" style=\"margin: 5px;\" target=\"_black\">沪江法语</a>  <a href=\"http://kr.hujiang.com\" style=\"margin: 5px;\" target=\"_black\">沪江韩语</a></div><hr style=\"border: 0.5px solid gray;\" />", 
  "title": "磁暴来袭（有声）"
 }
]